README.rst
setup.py
telwoord/__init__.py
telwoord/telwoord.py
telwoord.egg-info/PKG-INFO
telwoord.egg-info/SOURCES.txt
telwoord.egg-info/dependency_links.txt
telwoord.egg-info/pbr.json
telwoord.egg-info/top_level.txt