Metadata-Version: 1.1
Name: telwoord
Version: 0.4
Summary: Convert numbers into their Dutch written form
Home-page: https://github.com/wbolster/telwoord
Author: Wouter Bolsterlee
Author-email: uws@xs4all.nl
License: BSD
Platform: UNKNOWN
Classifier: Development Status :: 4 - Beta
Classifier: License :: OSI Approved :: BSD License
Classifier: Natural Language :: Dutch
Classifier: Operating System :: OS Independent
Classifier: Programming Language :: Python
Classifier: Programming Language :: Python :: 2
Classifier: Programming Language :: Python :: 3
Classifier: Topic :: Software Development :: Internationalization
Classifier: Topic :: Text Processing :: Filters
Classifier: Topic :: Text Processing :: Linguistic
